ansible_vault_tools/__init__.py
ansible_vault_tools/_helpers.py
ansible_vault_tools/main.py
ansible_vault_tools-0.2.0.dist-info/METADATA
ansible_vault_tools-0.2.0.dist-info/WHEEL
ansible_vault_tools-0.2.0.dist-info/entry_points.txt
ansible_vault_tools-0.2.0.dist-info/licenses/LICENSES/Apache-2.0.txt
ansible_vault_tools-0.2.0.dist-info/RECORD
